flirptu/__init__.py
flirptu/ptu.py
flirptu-0.0.1a2.dist-info/METADATA
flirptu-0.0.1a2.dist-info/RECORD
flirptu-0.0.1a2.dist-info/WHEEL
flirptu-0.0.1a2.dist-info/top_level.txt
