Metadata-Version: 2.1
Name: flirptu
Version: 0.0.1a2
Summary: Controller for FLIR E-series pan-tilt units
Home-page: https://github.com/hmorris94/FLIR-PTU-Python
Author: Hunter Morris
Author-email: hunterbmorris@gmail.com
License: UNKNOWN
Keywords: flir ptu pan-tilt
Platform: UNKNOWN
Classifier: Programming Language :: Python :: 3
Classifier: Natural Language :: English
Classifier: License :: OSI Approved :: MIT License
Classifier: Operating System :: OS Independent
Classifier: Intended Audience :: Science/Research
Classifier: Topic :: Scientific/Engineering :: Human Machine Interfaces
Classifier: Topic :: System :: Hardware
Requires-Python: >=3
Requires-Dist: pyserial
